mcp_image_super_resolution/__init__.py
mcp_image_super_resolution/server.py
mcp_image_super_resolution-0.1.2.dist-info/METADATA
mcp_image_super_resolution-0.1.2.dist-info/WHEEL
mcp_image_super_resolution-0.1.2.dist-info/entry_points.txt
mcp_image_super_resolution-0.1.2.dist-info/RECORD
