Metadata-Version: 2.4
Name: mcp-image-super-resolution
Version: 0.1.2
Summary: MCP服务器：图像超分辨率工具，提供AI图像放大和清晰度增强功能
Project-URL: Homepage, https://github.com/fengjinchao/mcp-image-super-resolution
Project-URL: Repository, https://github.com/fengjinchao/mcp-image-super-resolution
Project-URL: Documentation, https://github.com/fengjinchao/mcp-image-super-resolution#readme
Project-URL: Issues, https://github.com/fengjinchao/mcp-image-super-resolution/issues
Author-email: fengjinchao <fengjinchao@example.com>
License: MIT
Keywords: ai,aliyun,computer-vision,image,mcp,super-resolution,upscale
Classifier: Development Status :: 4 - Beta
Classifier: Intended Audience :: Developers
Classifier: License :: OSI Approved :: MIT License
Classifier: Programming Language :: Python :: 3
Classifier: Programming Language :: Python :: 3.10
Classifier: Programming Language :: Python :: 3.11
Classifier: Programming Language :: Python :: 3.12
Classifier: Topic :: Scientific/Engineering :: Artificial Intelligence
Classifier: Topic :: Scientific/Engineering :: Image Processing
Classifier: Topic :: Software Development :: Libraries :: Python Modules
Requires-Python: >=3.10
Requires-Dist: alibabacloud-imageenhan20190930>=2.0.10
Requires-Dist: alibabacloud-tea-openapi>=0.3.0
Requires-Dist: alibabacloud-tea-util>=0.3.0
Requires-Dist: alibabacloud-viapi20230117>=2.0.1
Requires-Dist: mcp[cli]>=1.0.0
